{
  "info": {
    "_postman_id": "frisan-api-collection",
    "name": "Frisan E-Commerce API",
    "description": "Comprehensive API collection for Frisan E-Commerce platform",
    "schema": "https://schema.getpostman.com/json/collection/v2.1.0/collection.json"
  },
  "item": [
    {
      "name": "User Authentication",
      "item": [
        {
          "name": "User Login",
          "request": {
            "method": "POST",
            "header": [
              {
                "key": "Content-Type",
                "value": "application/json"
              }
            ],
            "body": {
              "mode": "raw",
              "raw": "{\n  \"email\": \"user@example.com\",\n  \"password\": \"password123\"\n}"
            },
            "url": {
              "raw": "{{base_url}}/api/auth/login",
              "host": [
                "{{base_url}}"
              ],
              "path": [
                "api",
                "auth",
                "login"
              ]
            },
            "description": "Authenticate a user with email and password"
          },
          "response": []
        },
        {
          "name": "User Signup",
          "request": {
            "method": "POST",
            "header": [
              {
                "key": "Content-Type",
                "value": "application/json"
              }
            ],
            "body": {
              "mode": "raw",
              "raw": "{\n  \"email\": \"newuser@example.com\",\n  \"password\": \"securePassword123\",\n  \"confirm_password\": \"securePassword123\",\n  \"name\": \"Jane Doe\"\n}"
            },
            "url": {
              "raw": "{{base_url}}/api/auth/signup",
              "host": [
                "{{base_url}}"
              ],
              "path": [
                "api",
                "auth",
                "signup"
              ]
            },
            "description": "Register a new user account"
          },
          "response": []
        },
        {
          "name": "Verify Email",
          "request": {
            "method": "POST",
            "header": [
              {
                "key": "Content-Type",
                "value": "application/json"
              }
            ],
            "body": {
              "mode": "raw",
              "raw": "{\n  \"email\": \"user@example.com\",\n  \"code\": \"123456\"\n}"
            },
            "url": {
              "raw": "{{base_url}}/api/auth/verify-email",
              "host": [
                "{{base_url}}"
              ],
              "path": [
                "api",
                "auth",
                "verify-email"
              ]
            },
            "description": "Verify user email with 6-digit code"
          },
          "response": []
        },
        {
          "name": "Resend Verification Code",
          "request": {
            "method": "POST",
            "header": [
              {
                "key": "Content-Type",
                "value": "application/json"
              }
            ],
            "body": {
              "mode": "raw",
              "raw": "{\n  \"email\": \"user@example.com\"\n}"
            },
            "url": {
              "raw": "{{base_url}}/api/auth/resend-code",
              "host": [
                "{{base_url}}"
              ],
              "path": [
                "api",
                "auth",
                "resend-code"
              ]
            },
            "description": "Resend email verification code"
          },
          "response": []
        }
      ]
    },
    {
      "name": "User Password Recovery",
      "item": [
        {
          "name": "Forgot Password",
          "request": {
            "method": "POST",
            "header": [
              {
                "key": "Content-Type",
                "value": "application/json"
              }
            ],
            "body": {
              "mode": "raw",
              "raw": "{\n  \"email\": \"user@example.com\"\n}"
            },
            "url": {
              "raw": "{{base_url}}/api/auth/forgot-password",
              "host": [
                "{{base_url}}"
              ],
              "path": [
                "api",
                "auth",
                "forgot-password"
              ]
            },
            "description": "Initiate password reset process"
          },
          "response": []
        },
        {
          "name": "Verify Reset Token",
          "request": {
            "method": "POST",
            "header": [
              {
                "key": "Content-Type",
                "value": "application/json"
              }
            ],
            "body": {
              "mode": "raw",
              "raw": "{\n  \"token\": \"reset_token_string_here\"\n}"
            },
            "url": {
              "raw": "{{base_url}}/api/auth/verify-reset-token",
              "host": [
                "{{base_url}}"
              ],
              "path": [
                "api",
                "auth",
                "verify-reset-token"
              ]
            },
            "description": "Verify password reset token validity"
          },
          "response": []
        },
        {
          "name": "Reset Password",
          "request": {
            "method": "POST",
            "header": [
              {
                "key": "Content-Type",
                "value": "application/json"
              }
            ],
            "body": {
              "mode": "raw",
              "raw": "{\n  \"token\": \"reset_token_string_here\",\n  \"password\": \"newPassword123\",\n  \"confirm_password\": \"newPassword123\"\n}"
            },
            "url": {
              "raw": "{{base_url}}/api/auth/reset-password",
              "host": [
                "{{base_url}}"
              ],
              "path": [
                "api",
                "auth",
                "reset-password"
              ]
            },
            "description": "Reset user password with valid token"
          },
          "response": []
        }
      ]
    },
    {
      "name": "User Dashboard",
      "item": [
        {
          "name": "Get Dashboard",
          "request": {
            "method": "GET",
            "header": [
              {
                "key": "Authorization",
                "value": "Bearer {{user_token}}"
              }
            ],
            "url": {
              "raw": "{{base_url}}/api/dashboard",
              "host": [
                "{{base_url}}"
              ],
              "path": [
                "api",
                "dashboard"
              ]
            },
            "description": "Get user dashboard with profile and order statistics"
          },
          "response": []
        }
      ]
    },
    {
      "name": "Admin Authentication",
      "item": [
        {
          "name": "Admin Login",
          "request": {
            "method": "POST",
            "header": [
              {
                "key": "Content-Type",
                "value": "application/json"
              }
            ],
            "body": {
              "mode": "raw",
              "raw": "{\n  \"email\": \"admin@example.com\",\n  \"password\": \"adminPassword123\"\n}"
            },
            "url": {
              "raw": "{{base_url}}/api/admin/auth/login",
              "host": [
                "{{base_url}}"
              ],
              "path": [
                "api",
                "admin",
                "auth",
                "login"
              ]
            },
            "description": "Authenticate an admin user"
          },
          "response": []
        },
        {
          "name": "Get Authenticated Admin",
          "request": {
            "method": "GET",
            "header": [
              {
                "key": "Authorization",
                "value": "Bearer {{admin_token}}"
              }
            ],
            "url": {
              "raw": "{{base_url}}/api/admin/auth/me",
              "host": [
                "{{base_url}}"
              ],
              "path": [
                "api",
                "admin",
                "auth",
                "me"
              ]
            },
            "description": "Retrieve currently authenticated admin information"
          },
          "response": []
        },
        {
          "name": "Admin Logout",
          "request": {
            "method": "POST",
            "header": [
              {
                "key": "Authorization",
                "value": "Bearer {{admin_token}}"
              }
            ],
            "url": {
              "raw": "{{base_url}}/api/admin/auth/logout",
              "host": [
                "{{base_url}}"
              ],
              "path": [
                "api",
                "admin",
                "auth",
                "logout"
              ]
            },
            "description": "Log out the authenticated admin"
          },
          "response": []
        }
      ]
    },
    {
      "name": "Admin Password Recovery",
      "item": [
        {
          "name": "Admin Forgot Password",
          "request": {
            "method": "POST",
            "header": [
              {
                "key": "Content-Type",
                "value": "application/json"
              }
            ],
            "body": {
              "mode": "raw",
              "raw": "{\n  \"email\": \"admin@example.com\"\n}"
            },
            "url": {
              "raw": "{{base_url}}/api/admin/auth/forgot-password",
              "host": [
                "{{base_url}}"
              ],
              "path": [
                "api",
                "admin",
                "auth",
                "forgot-password"
              ]
            },
            "description": "Initiate admin password reset"
          },
          "response": []
        },
        {
          "name": "Admin Verify Reset Token",
          "request": {
            "method": "POST",
            "header": [
              {
                "key": "Content-Type",
                "value": "application/json"
              }
            ],
            "body": {
              "mode": "raw",
              "raw": "{\n  \"token\": \"reset_token_string_here\"\n}"
            },
            "url": {
              "raw": "{{base_url}}/api/admin/auth/verify-reset-token",
              "host": [
                "{{base_url}}"
              ],
              "path": [
                "api",
                "admin",
                "auth",
                "verify-reset-token"
              ]
            },
            "description": "Verify admin password reset token"
          },
          "response": []
        },
        {
          "name": "Admin Reset Password",
          "request": {
            "method": "POST",
            "header": [
              {
                "key": "Content-Type",
                "value": "application/json"
              }
            ],
            "body": {
              "mode": "raw",
              "raw": "{\n  \"token\": \"reset_token_string_here\",\n  \"password\": \"newPassword123\",\n  \"confirm_password\": \"newPassword123\"\n}"
            },
            "url": {
              "raw": "{{base_url}}/api/admin/auth/reset-password",
              "host": [
                "{{base_url}}"
              ],
              "path": [
                "api",
                "admin",
                "auth",
                "reset-password"
              ]
            },
            "description": "Reset admin password with valid token"
          },
          "response": []
        }
      ]
    },
    {
      "name": "Admin Dashboard",
      "item": [
        {
          "name": "Get Dashboard",
          "request": {
            "method": "GET",
            "header": [
              {
                "key": "Authorization",
                "value": "Bearer {{admin_token}}"
              }
            ],
            "url": {
              "raw": "{{base_url}}/api/admin/dashboard",
              "host": [
                "{{base_url}}"
              ],
              "path": [
                "api",
                "admin",
                "dashboard"
              ]
            },
            "description": "Get admin dashboard with business statistics"
          },
          "response": []
        }
      ]
    },
    {
      "name": "Admin Notifications",
      "item": [
        {
          "name": "Get All Notifications",
          "request": {
            "method": "GET",
            "header": [
              {
                "key": "Authorization",
                "value": "Bearer {{admin_token}}"
              }
            ],
            "url": {
              "raw": "{{base_url}}/api/admin/notifications?page=1&per_page=20&status=unread",
              "host": [
                "{{base_url}}"
              ],
              "path": [
                "api",
                "admin",
                "notifications"
              ],
              "query": [
                {
                  "key": "page",
                  "value": "1"
                },
                {
                  "key": "per_page",
                  "value": "20"
                },
                {
                  "key": "status",
                  "value": "unread",
                  "disabled": true
                }
              ]
            },
            "description": "Get paginated and grouped notifications"
          },
          "response": []
        },
        {
          "name": "Get Unread Notifications",
          "request": {
            "method": "GET",
            "header": [
              {
                "key": "Authorization",
                "value": "Bearer {{admin_token}}"
              }
            ],
            "url": {
              "raw": "{{base_url}}/api/admin/notifications/unread",
              "host": [
                "{{base_url}}"
              ],
              "path": [
                "api",
                "admin",
                "notifications",
                "unread"
              ]
            },
            "description": "Get only unread notifications"
          },
          "response": []
        },
        {
          "name": "Get Read Notifications",
          "request": {
            "method": "GET",
            "header": [
              {
                "key": "Authorization",
                "value": "Bearer {{admin_token}}"
              }
            ],
            "url": {
              "raw": "{{base_url}}/api/admin/notifications/read",
              "host": [
                "{{base_url}}"
              ],
              "path": [
                "api",
                "admin",
                "notifications",
                "read"
              ]
            },
            "description": "Get only read notifications"
          },
          "response": []
        },
        {
          "name": "Mark Notification as Read",
          "request": {
            "method": "POST",
            "header": [
              {
                "key": "Authorization",
                "value": "Bearer {{admin_token}}"
              }
            ],
            "url": {
              "raw": "{{base_url}}/api/admin/notifications/mark-as-read/1",
              "host": [
                "{{base_url}}"
              ],
              "path": [
                "api",
                "admin",
                "notifications",
                "mark-as-read",
                "1"
              ]
            },
            "description": "Mark a single notification as read"
          },
          "response": []
        },
        {
          "name": "Mark All Notifications as Read",
          "request": {
            "method": "POST",
            "header": [
              {
                "key": "Authorization",
                "value": "Bearer {{admin_token}}"
              }
            ],
            "url": {
              "raw": "{{base_url}}/api/admin/notifications/mark-all-as-read",
              "host": [
                "{{base_url}}"
              ],
              "path": [
                "api",
                "admin",
                "notifications",
                "mark-all-as-read"
              ]
            },
            "description": "Mark all notifications as read"
          },
          "response": []
        }
      ]
    },
    {
      "name": "Admin Products",
      "item": [
        {
          "name": "List All Products",
          "request": {
            "method": "GET",
            "header": [
              {
                "key": "Authorization",
                "value": "Bearer {{admin_token}}"
              }
            ],
            "url": {
              "raw": "{{base_url}}/api/admin/products?page=1&per_page=10",
              "host": [
                "{{base_url}}"
              ],
              "path": [
                "api",
                "admin",
                "products"
              ],
              "query": [
                {
                  "key": "page",
                  "value": "1"
                },
                {
                  "key": "per_page",
                  "value": "10"
                }
              ]
            },
            "description": "Get paginated list of all products"
          },
          "response": []
        },
        {
          "name": "Get Product Details",
          "request": {
            "method": "GET",
            "header": [
              {
                "key": "Authorization",
                "value": "Bearer {{admin_token}}"
              }
            ],
            "url": {
              "raw": "{{base_url}}/api/admin/products/1",
              "host": [
                "{{base_url}}"
              ],
              "path": [
                "api",
                "admin",
                "products",
                "1"
              ]
            },
            "description": "Get detailed information about a specific product"
          },
          "response": []
        },
        {
          "name": "Create Product",
          "request": {
            "method": "POST",
            "header": [
              {
                "key": "Content-Type",
                "value": "application/json"
              },
              {
                "key": "Authorization",
                "value": "Bearer {{admin_token}}"
              }
            ],
            "body": {
              "mode": "raw",
              "raw": "{\n  \"name\": \"Mechanical Keyboard\",\n  \"description\": \"RGB mechanical gaming keyboard with Cherry MX switches\",\n  \"price\": 12000,\n  \"cost_price\": 5000,\n  \"category_id\": 5,\n  \"quantity\": 30,\n  \"sku\": \"KEYBOARD-001\",\n  \"image_url\": \"/images/products/mechanical-keyboard.jpg\",\n  \"status\": \"active\"\n}"
            },
            "url": {
              "raw": "{{base_url}}/api/admin/products/store",
              "host": [
                "{{base_url}}"
              ],
              "path": [
                "api",
                "admin",
                "products",
                "store"
              ]
            },
            "description": "Create a new product"
          },
          "response": []
        },
        {
          "name": "Update Product",
          "request": {
            "method": "POST",
            "header": [
              {
                "key": "Content-Type",
                "value": "application/json"
              },
              {
                "key": "Authorization",
                "value": "Bearer {{admin_token}}"
              }
            ],
            "body": {
              "mode": "raw",
              "raw": "{\n  \"price\": 13500,\n  \"quantity\": 25,\n  \"status\": \"active\"\n}"
            },
            "url": {
              "raw": "{{base_url}}/api/admin/products/update/1",
              "host": [
                "{{base_url}}"
              ],
              "path": [
                "api",
                "admin",
                "products",
                "update",
                "1"
              ]
            },
            "description": "Update an existing product"
          },
          "response": []
        },
        {
          "name": "Delete Product",
          "request": {
            "method": "POST",
            "header": [
              {
                "key": "Authorization",
                "value": "Bearer {{admin_token}}"
              }
            ],
            "url": {
              "raw": "{{base_url}}/api/admin/products/delete/1",
              "host": [
                "{{base_url}}"
              ],
              "path": [
                "api",
                "admin",
                "products",
                "delete",
                "1"
              ]
            },
            "description": "Delete a product from the system"
          },
          "response": []
        },
        {
          "name": "Get Next Product ID",
          "request": {
            "method": "GET",
            "header": [
              {
                "key": "Authorization",
                "value": "Bearer {{admin_token}}"
              }
            ],
            "url": {
              "raw": "{{base_url}}/api/admin/products/next-id",
              "host": [
                "{{base_url}}"
              ],
              "path": [
                "api",
                "admin",
                "products",
                "next-id"
              ]
            },
            "description": "Get the next available product ID"
          },
          "response": []
        }
      ]
    }
  ],
  "variable": [
    {
      "key": "base_url",
      "value": "http://localhost:8000",
      "type": "string"
    },
    {
      "key": "user_token",
      "value": "",
      "type": "string"
    },
    {
      "key": "admin_token",
      "value": "",
      "type": "string"
    }
  ]
}
